{
  "parent": "./shield-adunian",
  "display": {
  "thirdperson_righthand": {
      "rotation": [33.5, -45, 0],
      "translation": [2, 1, 2.5]
    },
    "thirdperson_lefthand": {
      "rotation": [33.5, -45, 0],
      "translation": [2, 1, 2.5]
    },
        "firstperson_righthand": {
      "rotation": [0, 0, 0],
      "translation": [-1, -4, -3],
      "scale": [2, 2, 1]
    },
    "firstperson_lefthand": {
      "rotation": [0, 0, 0],
      "translation": [-1, -4, -3],
      "scale": [2, 2, 1]
    }
    }
}