{
  "texture_size": [32, 32],
  "textures": {
    "0": "optifine/cit/textures/adunian_shield"
  }
  ,
  "elements": [
    {
      "from": [1, 6, 7],
      "to": [15, 11, 8],
      "faces": {
        "north": {"uv": [0.5, 1.5, 7.5, 4], "texture": "#0"},
        "east": {"uv": [7.5, 1.5, 8, 4], "texture": "#0"},
        "south": {"uv": [8.5, 1.5, 15.5, 4], "texture": "#0"},
        "west": {"uv": [0, 1.5, 0.5, 4], "texture": "#0"},
        "up": {"uv": [0.5, 0, 7.5, 0.5], "rotation": 180, "texture": "#0"},
        "down": {"uv": [0.5, 10, 7.5, 10.5], "rotation": 180, "texture": "#0"}
      }
    }
    ,
    {
      "from": [2, 3, 7],
      "to": [14, 6, 8],
      "faces": {
        "north": {"uv": [1, 4, 7, 5.5], "texture": "#0"},
        "east": {"uv": [7.5, 4, 8, 5.5], "texture": "#0"},
        "south": {"uv": [9, 4, 15, 5.5], "texture": "#0"},
        "west": {"uv": [0, 4, 0.5, 5.5], "texture": "#0"},
        "down": {"uv": [1, 10, 7, 10.5], "rotation": 180, "texture": "#0"}
      }
    }
    ,
    {
      "from": [3, 1, 7],
      "to": [13, 3, 8],
      "faces": {
        "north": {"uv": [1.5, 5.5, 6.5, 6.5], "texture": "#0"},
        "east": {"uv": [7.5, 5.5, 8, 6.5], "texture": "#0"},
        "south": {"uv": [9.5, 5.5, 14.5, 6.5], "texture": "#0"},
        "west": {"uv": [0, 5.5, 0.5, 6.5], "texture": "#0"},
        "down": {"uv": [6.5, 10.5, 1.5, 10], "texture": "#0"}
      }
    }
    ,
    {
      "from": [3, 11, 7],
      "to": [13, 12, 8],
      "faces": {
        "north": {"uv": [1.5, 1, 6.5, 1.5], "texture": "#0"},
        "east": {"uv": [7.5, 1, 8, 1.5], "texture": "#0"},
        "south": {"uv": [10, 1, 14, 1.5], "texture": "#0"},
        "west": {"uv": [0, 1, 0.5, 1.5], "texture": "#0"},
        "up": {"uv": [2, 0, 6, 0.5], "rotation": 180, "texture": "#0"}
      }
    }
    ,
    {
      "from": [5, -3, 7],
      "to": [11, -1, 8],
      "faces": {
        "north": {"uv": [2.5, 7.5, 5.5, 8.5], "texture": "#0"},
        "east": {"uv": [0, 7.5, 0.5, 8.5], "texture": "#0"},
        "south": {"uv": [10.5, 7.5, 13.5, 8.5], "texture": "#0"},
        "west": {"uv": [7.5, 7.5, 8, 8.5], "texture": "#0"},
        "down": {"uv": [2.5, 10, 5.5, 10.5], "rotation": 180, "texture": "#0"}
      }
    }
    ,
    {
      "from": [6, -5, 7],
      "to": [10, -3, 8],
      "faces": {
        "north": {"uv": [3, 8.5, 5, 9.5], "texture": "#0"},
        "east": {"uv": [0, 8.5, 0.5, 9.5], "texture": "#0"},
        "south": {"uv": [11, 8.5, 13, 9.5], "texture": "#0"},
        "west": {"uv": [8, 9.5, 7.5, 8.5], "rotation": 180, "texture": "#0"},
        "down": {"uv": [3, 10, 5, 10.5], "rotation": 180, "texture": "#0"}
      }
    }
    ,
    {
      "from": [6, 12, 7],
      "to": [10, 13, 8],
      "faces": {
        "north": {"uv": [3, 0.5, 5, 1], "texture": "#0"},
        "east": {"uv": [7.5, 0.5, 8, 1], "texture": "#0"},
        "south": {"uv": [11, 0.5, 13, 1], "texture": "#0"},
        "west": {"uv": [0.5, 1, 0, 0.5], "rotation": 180, "texture": "#0"},
        "up": {"uv": [3, 0, 5, 0.5], "rotation": 180, "texture": "#0"}
      }
    }
    ,
    {
      "from": [7, -6, 7],
      "to": [9, -5, 8],
      "faces": {
        "north": {"uv": [3.5, 9.5, 4.5, 10], "texture": "#0"},
        "east": {"uv": [0, 9.5, 0.5, 10], "texture": "#0"},
        "south": {"uv": [11.5, 9.5, 12.5, 10], "texture": "#0"},
        "west": {"uv": [7.5, 9.5, 8, 10], "texture": "#0"},
        "down": {"uv": [3.5, 10, 4.5, 10.5], "rotation": 180, "texture": "#0"}
      }
    }
    ,
    {
      "from": [7, 8, 8],
      "to": [9, 9, 13],
      "faces": {
        "north": {"uv": [0, 0, 0, 0], "texture": "#0"},
        "east": {"uv": [4.5, 12, 5, 14.5], "rotation": 180, "texture": "#0"},
        "south": {"uv": [3.5, 14.5, 4.5, 15], "rotation": 90, "texture": "#0", "cullface": "up"},
        "west": {"uv": [3, 12, 3.5, 14.5], "texture": "#0"},
        "up": {"uv": [3.5, 12, 4.5, 14.5], "rotation": 270, "texture": "#0"},
        "down": {"uv": [3.5, 12, 4.5, 14.5], "rotation": 90, "texture": "#0"}
      }
    }
    ,
    {
      "from": [7, 3, 8],
      "to": [9, 4, 13],
      "faces": {
        "north": {"uv": [0, 0, 0, 0], "texture": "#0"},
        "east": {"uv": [4.5, 12, 5, 14.5], "rotation": 180, "texture": "#0"},
        "south": {"uv": [3.5, 14.5, 4.5, 15], "rotation": 90, "texture": "#0", "cullface": "up"},
        "west": {"uv": [3, 12, 3.5, 14.5], "texture": "#0"},
        "up": {"uv": [3.5, 12, 4.5, 14.5], "rotation": 270, "texture": "#0"},
        "down": {"uv": [3.5, 12, 4.5, 14.5], "rotation": 90, "texture": "#0"}
      }
    }
    ,
    {
      "from": [7, 4, 12],
      "to": [9, 8, 13],
      "faces": {
        "north": {"uv": [11.5, 12.5, 12.5, 14.5], "rotation": 180, "texture": "#0"},
        "east": {"uv": [12.5, 12.5, 13, 14.5], "texture": "#0"},
        "south": {"uv": [11.5, 12.5, 12.5, 14.5], "rotation": 180, "texture": "#0"},
        "west": {"uv": [11, 12.5, 11.5, 14.5], "texture": "#0"}
      }
    }
    ,
    {
      "from": [4, -1, 7],
      "to": [12, 1, 8],
      "faces": {
        "north": {"uv": [2, 6.5, 6, 7.5], "texture": "#0"},
        "east": {"uv": [7.5, 6.5, 8, 7.5], "texture": "#0"},
        "south": {"uv": [10, 6.5, 14, 7.5], "texture": "#0"},
        "west": {"uv": [0, 6.5, 0.5, 7.5], "texture": "#0"},
        "down": {"uv": [2, 10, 6, 10.5], "texture": "#0"}
      }
    }
  ]
  ,
  "gui_light": "front",
  "display": {
    "thirdperson_righthand": {
      "rotation": [0, -90, 0],
      "translation": [2, 0, 3]
    }
    ,
    "thirdperson_lefthand": {
      "rotation": [0, -90, 0],
      "translation": [2, 0, 3]
    }
    ,
    "firstperson_righthand": {
      "rotation": [0, -23, 0],
      "translation": [5, -6.5, 0],
      "scale": [2, 2, 1]
    }
    ,
    "firstperson_lefthand": {
      "rotation": [0, -23, 0],
      "translation": [5, -6.5, 0],
      "scale": [2, 2, 1]
    }
    ,
    "ground": {
      "translation": [0, 6, 0],
      "scale": [0.5, 0.5, 0.5]
    }
    ,
    "gui": {
      "rotation": [-45, 133, 30],
      "translation": [0.75, 2.25, 0],
      "scale": [0.75, 0.75, 0.75]
    }
    ,
    "fixed": {
      "translation": [0, 4, -1],
      "scale": [2, 2, 2]
    }
  }
}